{
    "id": 2,
    "query": "Question: Students watched a bird fly to and from a large bush every few minutes. The students told their teacher, \"The bird has a nest in that bush.\" This statement is an example of\n\nChoices:\nA: an inference made from observations.\nB: an observation made from predictions.\nC: a prediction made from data samples.\nD: a result made from inference.",
    "solution": "A",
    "style_name": "form_3_causal_chain",
    "steps": [
        "If a bird frequently flies to and from a bush, then it is likely using the bush for some purpose. If it happens repeatedly, then observers may infer a nest is present. Therefore, saying the bird has a nest in the bush is an inference made from observations."
    ]
}